{
  "generated_at": "2026-04-26T12:57:16.584531+00:00",
  "review": {
    "review_id": "r241-16x-secret-like-path-review-89983aa3",
    "generated_at": "2026-04-26T12:57:16.583922+00:00",
    "status": "reviewed_no_secret_like_content",
    "decision": "allow_closure_no_secret",
    "target_path": "frontend/.env.example",
    "target_exists": true,
    "target_is_tracked": true,
    "target_is_ignored": false,
    "r241_16w_status": "blocked_unknown_dirty_state",
    "r241_16w_decision": "block_closure_until_worktree_review",
    "r241_16w_failed_check": "no_secret_like_paths",
    "target_file_inspection": {
      "path": "frontend/.env.example",
      "exists": true,
      "is_file": true,
      "tracked": true,
      "ignored": false,
      "file_size_bytes": 1109,
      "line_count": 23,
      "diff_status": [
        "M\tfrontend/.env.example"
      ],
      "content_readable": true,
      "warnings": [],
      "errors": []
    },
    "scan_summary": {
      "total_lines": 23,
      "env_key_count": 0,
      "comment_count": 18,
      "empty_value_count": 0,
      "placeholder_count": 0,
      "real_secret_candidate_count": 0,
      "suspicious_value_count": 0,
      "warnings": [],
      "errors": []
    },
    "findings": [],
    "finding_count": 0,
    "real_secret_candidate_count": 0,
    "template_placeholder_count": 0,
    "empty_value_count": 0,
    "suspicious_value_count": 0,
    "finding_classification": {
      "classification": "no_secret_like_content",
      "risk_level": "low",
      "allow_closure": true,
      "warnings": [],
      "errors": []
    },
    "closure_reclassification": "no_secret_like_content",
    "closure_checks": [
      {
        "check_id": "r241_16w_condition_loaded",
        "passed": true,
        "risk_level": "medium",
        "description": "R241-16W condition matches expected secret-like path block",
        "observed_value": "True",
        "expected_value": "True",
        "evidence_refs": [],
        "required_for_closure": true,
        "blocked_reasons": [],
        "warnings": [],
        "errors": []
      },
      {
        "check_id": "target_file_readable",
        "passed": true,
        "risk_level": "high",
        "description": "Target env example is readable",
        "observed_value": "True",
        "expected_value": "True",
        "evidence_refs": [],
        "required_for_closure": true,
        "blocked_reasons": [],
        "warnings": [],
        "errors": []
      },
      {
        "check_id": "no_real_secret_candidates",
        "passed": true,
        "risk_level": "critical",
        "description": "No real secret candidates detected",
        "observed_value": "0",
        "expected_value": "0",
        "evidence_refs": [],
        "required_for_closure": true,
        "blocked_reasons": [],
        "warnings": [],
        "errors": []
      },
      {
        "check_id": "no_raw_values_emitted",
        "passed": true,
        "risk_level": "high",
        "description": "Findings use masked previews only",
        "observed_value": "masked",
        "expected_value": "masked",
        "evidence_refs": [],
        "required_for_closure": true,
        "blocked_reasons": [],
        "warnings": [],
        "errors": []
      }
    ],
    "receiver_next_steps": [
      "Do not commit or clean unrelated working tree files in this review.",
      "If accepted, re-run final closure re-evaluation with secret_template_path treated as external worktree condition."
    ],
    "safety_summary": {
      "git_commit_executed": false,
      "git_push_executed": false,
      "git_reset_restore_revert_executed": false,
      "git_am_apply_executed": false,
      "gh_workflow_run_executed": false,
      "secret_environment_read": false,
      "workflow_modified": false,
      "runtime_write": false,
      "audit_jsonl_write": false,
      "action_queue_write": false,
      "auto_fix_executed": false,
      "raw_secret_value_emitted": false
    },
    "validation_result": {
      "valid": true,
      "warnings": [],
      "errors": []
    },
    "warnings": [],
    "errors": []
  },
  "validation": {
    "valid": true,
    "warnings": [],
    "errors": []
  }
}